karton2/__init__.py
karton2/__version__.py
karton2/base.py
karton2/config.py
karton2/karton.py
karton2/logger.py
karton2/resource.py
karton2/task.py
karton2/test.py
karton2/utils.py
karton2/services/__init__.py
karton2/services/system.py
karton2-3.1.0.dist-info/METADATA
karton2-3.1.0.dist-info/WHEEL
karton2-3.1.0.dist-info/entry_points.txt
karton2-3.1.0.dist-info/top_level.txt
karton2-3.1.0.dist-info/RECORD
