Metadata-Version: 2.1
Name: karton2
Version: 3.1.0
Summary: Base library for karton subsystems
Home-page: UNKNOWN
Author: UNKNOWN
Author-email: UNKNOWN
License: UNKNOWN
Platform: UNKNOWN
Classifier: Programming Language :: Python
Classifier: Operating System :: OS Independent
Requires-Dist: redis
Requires-Dist: minio
Requires-Dist: mock (==3.0.5) ; python_version < "3"
